options_scraper/__init__.py
options_scraper/cli.py
options_scraper/scraper.py
options_scraper/serializer.py
options_scraper/utils.py
options_scraper-0.9.91.dist-info/METADATA
options_scraper-0.9.91.dist-info/WHEEL
options_scraper-0.9.91.dist-info/entry_points.txt
options_scraper-0.9.91.dist-info/top_level.txt
options_scraper-0.9.91.dist-info/RECORD
