Metadata-Version: 2.1
Name: options-scraper
Version: 0.9.91
Summary: NASDAQ Options chain scraper for https://old.nasdaq.com
Home-page: https://github.com/aosingh/options_scraper
Author: Abhishek Singh
Author-email: aosingh@asu.edu
Maintainer: Abhishek Singh
Maintainer-email: aosingh@asu.edu
License: GNU GPLv3
Keywords: nasdaq options chain scraper
Platform: UNKNOWN
Classifier: Development Status :: 4 - Beta
Classifier: Intended Audience :: Education
Classifier: Intended Audience :: Developers
Classifier: Intended Audience :: Financial and Insurance Industry
Classifier: License :: OSI Approved :: GNU General Public License v3 (GPLv3)
Classifier: Programming Language :: Python :: 3.7
Classifier: Programming Language :: Python :: 3.8
Classifier: Topic :: Office/Business :: Financial
Classifier: Topic :: Text Processing :: Markup :: HTML
Classifier: Operating System :: POSIX :: Linux
Classifier: Operating System :: Unix
Classifier: Operating System :: Microsoft :: Windows
Classifier: Operating System :: MacOS
